twitch/__init__.py
twitch/channel.py
twitch/chat.py
twitch/client.py
twitch/errors.py
twitch/gateway.py
twitch/http.py
twitch/py.typed
twitch/state.py
twitch/stream.py
twitch/user.py
twitch/utils.py
twitch/ext/bot/__init__.py
twitch/ext/bot/bot.py
twitch/ext/oauth/__init__.py
twitch/ext/oauth/enums.py
twitch/ext/oauth/http.py
twitch/ext/oauth/oauth.py
twitch/types/__init__.py
twitch/types/activity.py
twitch/types/analytics.py
twitch/types/bits.py
twitch/types/channels.py
twitch/types/chat.py
twitch/types/interaction.py
twitch/types/moderation.py
twitch/types/search.py
twitch/types/streams.py
twitch/types/users.py
twitch/types/eventsub/__init__.py
twitch/types/eventsub/activity.py
twitch/types/eventsub/bits.py
twitch/types/eventsub/channels.py
twitch/types/eventsub/chat.py
twitch/types/eventsub/interaction.py
twitch/types/eventsub/moderation.py
twitch/types/eventsub/streams.py
twitch/types/eventsub/users.py
twitchify-3.2.0.dist-info/LICENSE
twitchify-3.2.0.dist-info/METADATA
twitchify-3.2.0.dist-info/WHEEL
twitchify-3.2.0.dist-info/top_level.txt
twitchify-3.2.0.dist-info/RECORD
